compas_tno/__init__.py
compas_tno/algorithms/__init__.py
compas_tno/algorithms/equilibrium.py
compas_tno/algorithms/independents.py
compas_tno/analysis/__init__.py
compas_tno/analysis/analysis.py
compas_tno/optimisers/__init__.py
compas_tno/optimisers/optimiser.py
compas_tno/problems/__init__.py
compas_tno/problems/bounds_update.py
compas_tno/problems/callbacks.py
compas_tno/problems/constraints.py
compas_tno/problems/derivatives.py
compas_tno/problems/jacobian.py
compas_tno/problems/objectives.py
compas_tno/problems/problems.py
compas_tno/problems/setup.py
compas_tno/problems/startingpoint.py
compas_tno/solvers/__init__.py
compas_tno/solvers/cvxpy.py
compas_tno/solvers/ipopt.py
compas_tno/solvers/post_process.py
compas_tno/solvers/scipy.py
compas_tno/utilities/__init__.py
compas_tno/utilities/constraints.py
compas_tno/utilities/form.py
compas_tno/utilities/functions.py
compas_tno/utilities/interpolation.py
compas_tno/utilities/json.py
compas_tno/utilities/stiffness.py
compas_tno/utilities/symmetry.py
compas_tno-0.3.0.dist-info/licenses/AUTHORS.md
compas_tno-0.3.0.dist-info/licenses/LICENSE
compas_tno-0.3.0.dist-info/METADATA
compas_tno-0.3.0.dist-info/WHEEL
compas_tno-0.3.0.dist-info/top_level.txt
compas_tno-0.3.0.dist-info/RECORD
