Metadata-Version: 2.4
Name: compas_tno
Version: 0.3.0
Summary: This package performs masonry assessment by menans of NLP with Funicular Thrust Networks.
Author-email: Ricardo Maia Avelino <maia@arch.ethz.ch>
License: MIT License
Project-URL: Homepage, https://blockresearchgroup.github.io/compas_tno
Project-URL: Documentation, https://blockresearchgroup.github.io/compas_tno
Project-URL: Repository, https://github.com/blockresearchgroup/compas_tno.git
Project-URL: Changelog, https://github.com/blockresearchgroup/compas_tno/blob/main/CHANGELOG.md
Classifier: Development Status :: 4 - Beta
Classifier: Topic :: Scientific/Engineering
Classifier: Programming Language :: Python
Classifier: Programming Language :: Python :: 3
Classifier: Programming Language :: Python :: 3.9
Classifier: Programming Language :: Python :: 3.10
Classifier: Programming Language :: Python :: 3.11
Requires-Python: >=3.9
License-File: LICENSE
License-File: AUTHORS.md
Requires-Dist: compas
Requires-Dist: compas_tna
Requires-Dist: cvxpy
Provides-Extra: dev
Requires-Dist: bump-my-version; extra == "dev"
Requires-Dist: compas_invocations2; extra == "dev"
Requires-Dist: compas_notebook; extra == "dev"
Requires-Dist: compas_viewer; extra == "dev"
Requires-Dist: invoke>=0.14; extra == "dev"
Requires-Dist: ruff; extra == "dev"
Requires-Dist: sphinx_compas2_theme; extra == "dev"
Requires-Dist: twine; extra == "dev"
Requires-Dist: wheel; extra == "dev"
Dynamic: license-file
